{
  "df": "df-heylou-9os-coupling-validator",
  "ts": "2026-06-15T22:43:25.092074+00:00",
  "crux": "[CRUX-MK]",
  "winner_provider": "codex",
  "winner_tests_passed": true,
  "incumbent_q": 1510.0,
  "winner_q": 1520.0,
  "improved": true,
  "variants": [
    {
      "provider": "incumbent",
      "parse_ok": true,
      "tests_passed": true,
      "n_tests": 1,
      "n_assert": 17,
      "coverage_pct": 98.0,
      "q": 1510.0,
      "error": null
    },
    {
      "provider": "codex",
      "parse_ok": true,
      "tests_passed": true,
      "n_tests": 3,
      "n_assert": 11,
      "coverage_pct": 100.0,
      "q": 1520.0,
      "error": null
    },
    {
      "provider": "sonnet",
      "parse_ok": false,
      "tests_passed": false,
      "n_tests": 0,
      "n_assert": null,
      "coverage_pct": null,
      "q": 0.0,
      "error": "kein 2-Block-Output (nach Retry)"
    }
  ],
  "canonical_verify": {
    "parse_ok": true,
    "tests_passed": true
  }
}